tipico/__init__.py
tipico/__version__.py
tipico/calibration/__init__.py
tipico/calibration/abstract_calibration_manager.py
tipico/calibration/calibration_manager.py
tipico/calibration/in_memory_calibration_manager.py
tipico/client/__init__.py
tipico/client/abstract_instrument_client.py
tipico/client/instrument_client.py
tipico/conf/tipico.conf
tipico/gui/__init__.py
tipico/gui/basic_pyqt5.py
tipico/gui/basic_pyside2.py
tipico/gui/basic_qt.py
tipico/types/__init__.py
tipico/types/encoder_calibration.py
tipico/types/instrument_status.py
tipico/utils/__init__.py
tipico/utils/constants.py
tipico/utils/timeout.py
tipico-0.16.1.dist-info/LICENSE
tipico-0.16.1.dist-info/METADATA
tipico-0.16.1.dist-info/WHEEL
tipico-0.16.1.dist-info/entry_points.txt
tipico-0.16.1.dist-info/top_level.txt
tipico-0.16.1.dist-info/RECORD
