Metadata-Version: 2.1
Name: tipico
Version: 0.16.1
Summary: useless client of a simulated device with PLICO
Home-page: https://github.com/lbusoni/tipico
Author: Lorenzo Busoni
Author-email: lorenzo.busoni@inaf.it
License: MIT
Keywords: plico,laboratory,instrumentation control
Platform: UNKNOWN
Classifier: Development Status :: 4 - Beta
Classifier: Operating System :: POSIX :: Linux
Classifier: Programming Language :: Python :: 2.7
Classifier: Programming Language :: Python :: 3
License-File: LICENSE
Requires-Dist: plico (>=0.20)
Requires-Dist: numpy
Requires-Dist: six
Requires-Dist: astropy
Requires-Dist: pyside2
Requires-Dist: Qt.py
